django_page_resolver/__init__.py
django_page_resolver/locale/de/LC_MESSAGES/django.mo
django_page_resolver/locale/de/LC_MESSAGES/django.po
django_page_resolver/locale/en/LC_MESSAGES/django.mo
django_page_resolver/locale/en/LC_MESSAGES/django.po
django_page_resolver/locale/es/LC_MESSAGES/django.mo
django_page_resolver/locale/es/LC_MESSAGES/django.po
django_page_resolver/locale/fr/LC_MESSAGES/django.mo
django_page_resolver/locale/fr/LC_MESSAGES/django.po
django_page_resolver/locale/it/LC_MESSAGES/django.mo
django_page_resolver/locale/it/LC_MESSAGES/django.po
django_page_resolver/locale/pl/LC_MESSAGES/django.mo
django_page_resolver/locale/pl/LC_MESSAGES/django.po
django_page_resolver/locale/uk/LC_MESSAGES/django.mo
django_page_resolver/locale/uk/LC_MESSAGES/django.po
django_page_resolver/models.py
django_page_resolver/resolvers.py
django_page_resolver/static/resolvers/css/page_resolvers.css
django_page_resolver/static/resolvers/js/page_resolvers.js
django_page_resolver/templatetags/__init__.py
django_page_resolver/templatetags/page_resolvers.py
django_page_resolver/utils.py
django_page_resolver-0.2.0.dist-info/LICENSE
django_page_resolver-0.2.0.dist-info/METADATA
django_page_resolver-0.2.0.dist-info/WHEEL
django_page_resolver-0.2.0.dist-info/RECORD
