Metadata-Version: 2.3
Name: django-page-resolver
Version: 0.2.0
Summary: Utility class for Django that helps determine the page number on which a specific object appears in a paginated list, either from a QuerySet or via a ForeignKey relationship.
License: MIT
Author: StanislavJPG
Author-email: samper.stas@gmail.com
Requires-Python: >=3.10
Classifier: License :: OSI Approved :: MIT License
Classifier: Programming Language :: Python :: 3
Classifier: Programming Language :: Python :: 3.10
Classifier: Programming Language :: Python :: 3.11
Classifier: Programming Language :: Python :: 3.12
Classifier: Programming Language :: Python :: 3.13
Requires-Dist: django
